srtlst/__init__.py
srtlst/bisect.py
srtlst/collections_abc.py
srtlst/protocols.py
srtlst/py.typed
srtlst/sorted_list.py
srtlst/sorted_list_by_key.py
srtlst-0.2.0.dist-info/LICENSE
srtlst-0.2.0.dist-info/METADATA
srtlst-0.2.0.dist-info/WHEEL
srtlst-0.2.0.dist-info/RECORD
