Metadata-Version: 2.1
Name: srtlst
Version: 0.2.0
Summary: a simple, generically type-annotated, sorted list
Home-page: https://github.com/exoriente/srtlst
License: MIT
Keywords: sorted,list,simple,container,sorting,bisect,typed,mypy
Author: exoriente
Requires-Python: >=3.8,<4.0
Classifier: Intended Audience :: Developers
Classifier: License :: OSI Approved :: MIT License
Classifier: Programming Language :: Python :: 3
Classifier: Programming Language :: Python :: 3.8
Classifier: Programming Language :: Python :: 3.9
Classifier: Programming Language :: Python :: 3.10
Classifier: Programming Language :: Python :: 3.11
Classifier: Programming Language :: Python :: 3 :: Only
Classifier: Programming Language :: Python :: 3.10
Classifier: Programming Language :: Python :: 3.11
Classifier: Programming Language :: Python :: 3.12
Classifier: Topic :: Software Development :: Libraries
Classifier: Typing :: Typed
Project-URL: Repository, https://github.com/exoriente/srtlst
